jimo_repositories/__init.py
jimo_repositories/argsinitialiser.py
jimo_repositories/fileinfo.py
jimo_repositories/repository.py
jimobama_repositories/__init.py
jimobama_repositories/argsinitialiser.py
jimobama_repositories/fileinfo.py
jimobama_repositories/repository.py
jimobama_repositories-1.0.0.dist-info/METADATA
jimobama_repositories-1.0.0.dist-info/WHEEL
jimobama_repositories-1.0.0.dist-info/top_level.txt
jimobama_repositories-1.0.0.dist-info/RECORD
